ChangeLog
LISEZMOI.html
LISEZMOI.txt
MANIFEST.in
README.txt
index.html
setup.py
ts2avi.py
ts2avi.egg-info/PKG-INFO
ts2avi.egg-info/SOURCES.txt
ts2avi.egg-info/dependency_links.txt
ts2avi.egg-info/top_level.txt