Metadata-Version: 1.0
Name: ts2avi
Version: 0.1.1
Summary: A TS to AVI converter based on mplayer
Home-page: http://pypi.python.org/pypi
Author: Stephane Bugat
Author-email: stephane.bugat@free.fr
License: UNKNOWN
Platform: UNKNOWN
Classifier: Programming Language :: Python :: 2.7
Classifier: Development Status :: 4 - Beta
Classifier: Environment :: Console
Classifier: Intended Audience :: End Users/Desktop
Classifier: License :: OSI Approved :: GNU General Public License (GPL)
Classifier: Natural Language :: English
Classifier: Operating System :: POSIX
Classifier: Topic :: Multimedia :: Video :: Conversion
